smartprinter/__init__.py
smartprinter/commons.py
smartprinter/printers.py
smartprinter-0.3.1.dist-info/licenses/LICENSE
smartprinter-0.3.1.dist-info/METADATA
smartprinter-0.3.1.dist-info/WHEEL
smartprinter-0.3.1.dist-info/top_level.txt
smartprinter-0.3.1.dist-info/RECORD
