Metadata-Version: 2.4
Name: smartprinter
Version: 0.3.1
Summary: Cross-platform smart printer for console applications
Home-page: https://github.com/smartlegionlab/smartprinter
Author: A.A. Suvorov
Author-email: smartlegiondev@gmail.com
License: BSD 3-Clause License
Project-URL: Documentation, https://github.com/smartlegionlab/smartprinter/blob/master/README.md
Project-URL: Release notes, https://github.com/smartlegionlab/smartprinter/releases
Keywords: smart print,printer,smartlegionlab
Classifier: Development Status :: 5 - Production/Stable
Classifier: Environment :: Console
Classifier: Intended Audience :: End Users/Desktop
Classifier: Intended Audience :: System Administrators
Classifier: License :: OSI Approved :: BSD License
Classifier: Natural Language :: English
Classifier: Operating System :: OS Independent
Classifier: Operating System :: Microsoft :: Windows
Classifier: Operating System :: POSIX :: Linux
Classifier: Programming Language :: Python :: 3 :: Only
Classifier: Topic :: Software Development :: Libraries :: Python Modules
Classifier: Topic :: Utilities
Requires-Python: >=3.6
License-File: LICENSE
Requires-Dist: click~=8.0.1
Dynamic: license-file
